sphinxcontrib_inherit-0.1.0-nspkg.pth
sphinxcontrib/inherit/__init__.py
sphinxcontrib/inherit/directives.py
sphinxcontrib/inherit/nodes.py
sphinxcontrib/inherit/path.py
sphinxcontrib/inherit/transforms.py
sphinxcontrib_inherit-0.1.0.dist-info/DESCRIPTION.rst
sphinxcontrib_inherit-0.1.0.dist-info/METADATA
sphinxcontrib_inherit-0.1.0.dist-info/RECORD
sphinxcontrib_inherit-0.1.0.dist-info/WHEEL
sphinxcontrib_inherit-0.1.0.dist-info/metadata.json
sphinxcontrib_inherit-0.1.0.dist-info/namespace_packages.txt
sphinxcontrib_inherit-0.1.0.dist-info/top_level.txt
test/__init__.py
test/test_builders.py
test/test_directive.py
test/test_modules.py
test/test_path.py
